exparso/__init__.py
exparso/core/__init__.py
exparso/core/parse_core_service.py
exparso/core/type.py
exparso/core/context/__init__.py
exparso/core/context/update_context.py
exparso/core/docs_type/__init__.py
exparso/core/docs_type/judge_document_type.py
exparso/core/parse/__init__.py
exparso/core/parse/parse_document.py
exparso/core/prompt/__init__.py
exparso/core/prompt/default_prompt.py
exparso/core/prompt/prompt.py
exparso/llm/__init__.py
exparso/llm/claude.py
exparso/llm/gemini.py
exparso/llm/llm_factory.py
exparso/llm/openai.py
exparso/loader/__init__.py
exparso/loader/csv_loader.py
exparso/loader/docx_loader.py
exparso/loader/image_loader.py
exparso/loader/loader_factory.py
exparso/loader/pdf_loader.py
exparso/loader/pptx_loader.py
exparso/loader/text_file_loader.py
exparso/loader/xlsx_loader.py
exparso/model/__init__.py
exparso/model/cost.py
exparso/model/document.py
exparso/model/image.py
exparso/model/llm.py
exparso/model/page_contents.py
exparso/model/page_loader.py
exparso-0.0.2.dist-info/METADATA
exparso-0.0.2.dist-info/WHEEL
exparso-0.0.2.dist-info/licenses/LICENSE
exparso-0.0.2.dist-info/RECORD
