Metadata-Version: 2.4
Name: exparso
Version: 0.0.2
Summary: Analyzing and parsing documents
License-Expression: MIT
License-File: LICENSE
Keywords: langchain,openai,openpyxl,pdf,pdfplumber,pillow
Requires-Python: >=3.10
Requires-Dist: langchain>=0.3.14
Requires-Dist: openpyxl>=3.1.5
Requires-Dist: pdfplumber>=0.11.4
Requires-Dist: pillow>=10.4.0
